{
  "version": 1,
  "generated_at": "2026-04-17T19:20:58Z",
  "repo_root": "/home/rowan/womanvshorseVC",
  "audit_package_commit": "b2205a14fc57390317ff7b52a5c79e7a6a29adf4+dirty:0863e004cc5b",
  "allowed_classes": [
    "managed_blocker",
    "manual_prerequisite_blocker",
    "source_follow_up",
    "process_state_only",
    "advisory"
  ],
  "finding_count": 5,
  "findings": [
    {
      "code": "SKILL001",
      "severity": "warning",
      "disposition_class": "managed_blocker",
      "legacy_disposition_class": "managed_blocker",
      "route": "scafforge-repair",
      "repair_class": "safe Scafforge package change",
      "evidence_grade": "repo-state validation",
      "source_files": [
        ".opencode/skills/stack-standards/SKILL.md"
      ],
      "provenance": "script"
    },
    {
      "code": "SKILL003",
      "severity": "warning",
      "disposition_class": "managed_blocker",
      "legacy_disposition_class": "managed_blocker",
      "route": "scafforge-repair",
      "repair_class": "safe Scafforge package change",
      "evidence_grade": "repo-state validation",
      "source_files": [
        ".opencode/agents/wvhvc-team-leader.md"
      ],
      "provenance": "script"
    },
    {
      "code": "EXEC-BLENDER-001",
      "severity": "error",
      "disposition_class": "source_follow_up",
      "legacy_disposition_class": "source_follow_up",
      "route": "ticket-pack-builder",
      "repair_class": "generated-repo remediation ticket",
      "evidence_grade": "repo-state validation",
      "source_files": [
        ".opencode/meta/asset-pipeline-bootstrap.json",
        "assets/pipeline.json",
        ".blender-mcp/audit/audit_20260409.jsonl",
        ".blender-mcp/audit/audit_20260410.jsonl",
        ".blender-mcp/audit/audit_20260411.jsonl",
        ".blender-mcp/audit/audit_20260417.jsonl"
      ],
      "provenance": "script"
    },
    {
      "code": "EXEC-REMED-001",
      "severity": "error",
      "disposition_class": "source_follow_up",
      "legacy_disposition_class": "source_follow_up",
      "route": "ticket-pack-builder",
      "repair_class": "generated-repo remediation ticket",
      "evidence_grade": "repo-state validation",
      "source_files": [
        "tickets/manifest.json",
        ".opencode/state/reviews/remed-010-review-review.md"
      ],
      "provenance": "script"
    },
    {
      "code": "EXEC-REMED-001",
      "severity": "error",
      "disposition_class": "source_follow_up",
      "legacy_disposition_class": "source_follow_up",
      "route": "ticket-pack-builder",
      "repair_class": "generated-repo remediation ticket",
      "evidence_grade": "repo-state validation",
      "source_files": [
        "tickets/manifest.json",
        ".opencode/state/reviews/remed-014-review-ticket-reconciliation.md"
      ],
      "provenance": "script"
    }
  ],
  "counts": {
    "managed_blocker": 2,
    "manual_prerequisite_blocker": 0,
    "source_follow_up": 3,
    "process_state_only": 0,
    "advisory": 0
  },
  "shadow_mode_deltas": []
}
