{
  "version": 1,
  "generated_at": "2026-04-16T14:46:46Z",
  "repo_root": "/home/rowan/womanvshorseVC",
  "audit_package_commit": "2bdef2533fc214601e4bc795eb74b0520494e382+dirty:66df35729800",
  "allowed_classes": [
    "managed_blocker",
    "manual_prerequisite_blocker",
    "source_follow_up",
    "process_state_only",
    "advisory"
  ],
  "finding_count": 7,
  "findings": [
    {
      "code": "SKILL002",
      "severity": "warning",
      "disposition_class": "manual_prerequisite_blocker",
      "legacy_disposition_class": "managed_blocker",
      "route": "scafforge-repair",
      "repair_class": "safe Scafforge package change",
      "evidence_grade": "repo-state validation",
      "source_files": [
        ".opencode/agents/blender-asset-creator.md"
      ],
      "provenance": "script"
    },
    {
      "code": "FINISH002",
      "severity": "error",
      "disposition_class": "managed_blocker",
      "legacy_disposition_class": "managed_blocker",
      "route": "scafforge-repair",
      "repair_class": "safe Scafforge package change",
      "evidence_grade": "repo-state validation",
      "source_files": [
        "docs/spec/CANONICAL-BRIEF.md"
      ],
      "provenance": "script"
    },
    {
      "code": "EXEC-BLENDER-001",
      "severity": "error",
      "disposition_class": "source_follow_up",
      "legacy_disposition_class": "source_follow_up",
      "route": "ticket-pack-builder",
      "repair_class": "generated-repo remediation ticket",
      "evidence_grade": "repo-state validation",
      "source_files": [
        ".opencode/meta/asset-pipeline-bootstrap.json",
        "assets/pipeline.json",
        ".blender-mcp/audit/audit_20260409.jsonl",
        ".blender-mcp/audit/audit_20260410.jsonl",
        ".blender-mcp/audit/audit_20260411.jsonl"
      ],
      "provenance": "script"
    },
    {
      "code": "EXEC-REMED-001",
      "severity": "error",
      "disposition_class": "source_follow_up",
      "legacy_disposition_class": "source_follow_up",
      "route": "ticket-pack-builder",
      "repair_class": "generated-repo remediation ticket",
      "evidence_grade": "repo-state validation",
      "source_files": [
        "tickets/manifest.json",
        ".opencode/state/reviews/remed-001-review-ticket-reconciliation.md"
      ],
      "provenance": "script"
    },
    {
      "code": "EXEC-REMED-001",
      "severity": "error",
      "disposition_class": "source_follow_up",
      "legacy_disposition_class": "source_follow_up",
      "route": "ticket-pack-builder",
      "repair_class": "generated-repo remediation ticket",
      "evidence_grade": "repo-state validation",
      "source_files": [
        "tickets/manifest.json",
        ".opencode/state/reviews/remed-003-review-ticket-reconciliation.md"
      ],
      "provenance": "script"
    },
    {
      "code": "CYCLE002",
      "severity": "error",
      "disposition_class": "manual_prerequisite_blocker",
      "legacy_disposition_class": "managed_blocker",
      "route": "manual-prerequisite",
      "repair_class": "Scafforge package work required before the next subject-repo run",
      "evidence_grade": "repo-state validation",
      "source_files": [
        "diagnosis/20260416-144639/manifest.json",
        ".opencode/meta/bootstrap-provenance.json"
      ],
      "provenance": "script"
    },
    {
      "code": "SESSION003",
      "severity": "error",
      "disposition_class": "manual_prerequisite_blocker",
      "legacy_disposition_class": "managed_blocker",
      "route": "ticket-pack-builder",
      "repair_class": "generated-repo remediation ticket",
      "evidence_grade": "transcript-backed and repo-validated",
      "source_files": [
        "wvhvclogblender1.md"
      ],
      "provenance": "script"
    }
  ],
  "counts": {
    "managed_blocker": 1,
    "manual_prerequisite_blocker": 3,
    "source_follow_up": 3,
    "process_state_only": 0,
    "advisory": 0
  },
  "shadow_mode_deltas": [
    {
      "code": "SKILL002",
      "legacy_disposition_class": "managed_blocker",
      "disposition_class": "manual_prerequisite_blocker",
      "route": "scafforge-repair",
      "reason": "Legacy prefix classification would label SKILL002 as managed_blocker, but the authoritative bundle assigns manual_prerequisite_blocker."
    },
    {
      "code": "CYCLE002",
      "legacy_disposition_class": "managed_blocker",
      "disposition_class": "manual_prerequisite_blocker",
      "route": "manual-prerequisite",
      "reason": "Legacy prefix classification would label CYCLE002 as managed_blocker, but the authoritative bundle assigns manual_prerequisite_blocker."
    },
    {
      "code": "SESSION003",
      "legacy_disposition_class": "managed_blocker",
      "disposition_class": "manual_prerequisite_blocker",
      "route": "ticket-pack-builder",
      "reason": "Legacy prefix classification would label SESSION003 as managed_blocker, but the authoritative bundle assigns manual_prerequisite_blocker."
    }
  ]
}
